chemloader/__init__.py
chemloader/config.py
chemloader/dataloader.py
chemloader/datasets/__init__.py
chemloader/datasets/_local/Lipophilicity.csv
chemloader/datasets/_local/ci034243xsi20040112_053635.txt
chemloader/datasets/chemical/__init__.py
chemloader/datasets/chemical/lipophilicity.py
chemloader/datasets/chemical/nmr/__init__.py
chemloader/datasets/chemical/nmr/mixed.py
chemloader/datasets/chemical/nmr/phosphorus.py
chemloader/datasets/chemical/pka.py
chemloader/datasets/chemical/quantumemchanics.py
chemloader/datasets/chemical/solubility/ESOL.py
chemloader/datasets/chemical/solubility/FreeSolv.py
chemloader/datasets/chemical/solubility/__init__.py
chemloader/datasets/medical/__init__.py
chemloader/datasets/medical/tox21.py
chemloader/datasets/pysical/__init__.py
chemloader/datasets/pysical/fp.py
chemloader/datasets/pysical/logp.py
chemloader/datasets/pysical/mp.py
chemloader/pipeline/__init__.py
chemloader/pipeline/download.py
chemloader/pipeline/reader.py
chemloader/pipeline/setup.py
chemloader/storage/__init__.py
chemloader/storage/base.py
chemloader/storage/inmemory.py
chemloader/storage/molpickle.py
chemloader-0.1.4.dist-info/LICENSE
chemloader-0.1.4.dist-info/METADATA
chemloader-0.1.4.dist-info/WHEEL
chemloader-0.1.4.dist-info/RECORD
